datamaestro/__init__.py
datamaestro/__main__.py
datamaestro/context.py
datamaestro/definitions.py
datamaestro/record.py
datamaestro/registry.py
datamaestro/search.py
datamaestro/settings.py
datamaestro/sphinx.py
datamaestro/utils.py
datamaestro/v2.md
datamaestro/version.py
datamaestro/annotations/__init__.py
datamaestro/annotations/agreement.py
datamaestro/commands/__init__.py
datamaestro/commands/mainstyle.css
datamaestro/commands/site.py
datamaestro/data/__init__.py
datamaestro/data/csv.py
datamaestro/data/huggingface.py
datamaestro/data/ml.py
datamaestro/data/tensor.py
datamaestro/download/__init__.py
datamaestro/download/archive.py
datamaestro/download/custom.py
datamaestro/download/huggingface.py
datamaestro/download/links.py
datamaestro/download/manual.py
datamaestro/download/multiple.py
datamaestro/download/single.py
datamaestro/download/sync.py
datamaestro/download/todo.py
datamaestro/download/wayback.py
datamaestro/stream/__init__.py
datamaestro/stream/compress.py
datamaestro/stream/lines.py
datamaestro/templates/dataset.py
datamaestro/test/__init__.py
datamaestro/test/checks.py
datamaestro/test/conftest.py
datamaestro/test/test_annotations.py
datamaestro/test/test_download_handlers.py
datamaestro/test/test_record.py
datamaestro/test/test_resource.py
datamaestro-1.7.4.dist-info/METADATA
datamaestro-1.7.4.dist-info/WHEEL
datamaestro-1.7.4.dist-info/entry_points.txt
datamaestro-1.7.4.dist-info/licenses/LICENSE
datamaestro-1.7.4.dist-info/RECORD
