Metadata-Version: 2.4
Name: datamaestro
Version: 1.7.4
Summary: Add your description here
Author-email: Benjamin Piwowarski <benjamin@piwowarski.fr>
License-File: LICENSE
Classifier: Development Status :: 4 - Beta
Classifier: Intended Audience :: Science/Research
Classifier: License :: OSI Approved :: GNU General Public License v3 (GPLv3)
Classifier: Operating System :: OS Independent
Classifier: Programming Language :: Python
Classifier: Programming Language :: Python :: 3
Classifier: Topic :: Software Development :: Libraries :: Python Modules
Requires-Python: >=3.10
Requires-Dist: bitmath>=1.3.3.1
Requires-Dist: cached-property>=2.0.1
Requires-Dist: click>=8.2.1
Requires-Dist: docstring-parser>=0.16
Requires-Dist: experimaestro>=1.8.9
Requires-Dist: marshmallow>=3.26.1
Requires-Dist: mkdocs-material>=9.6.15
Requires-Dist: mkdocs>=1.6.1
Requires-Dist: numpy
Requires-Dist: pymdown-extensions>=10.16
Requires-Dist: requests>=2.32.4
Requires-Dist: tqdm>=4.67.1
Requires-Dist: urllib3>=2.5.0
Provides-Extra: docs
Requires-Dist: myst-parser>0.18; extra == 'docs'
Requires-Dist: sphinx-codeautolink>=0.15; extra == 'docs'
Requires-Dist: sphinx-rtd-theme==1.2.2; extra == 'docs'
Requires-Dist: sphinx-toolbox>=4.1.2; extra == 'docs'
Requires-Dist: sphinx>=4.2; extra == 'docs'
